paymongo_wrapper/__init__.py
paymongo_wrapper/exceptions.py
paymongo_wrapper/service.py
paymongo_wrapper-1.1.1.dist-info/licenses/LICENSE
paymongo_wrapper-1.1.1.dist-info/METADATA
paymongo_wrapper-1.1.1.dist-info/WHEEL
paymongo_wrapper-1.1.1.dist-info/top_level.txt
paymongo_wrapper-1.1.1.dist-info/RECORD
