Metadata-Version: 2.4
Name: paymongo-wrapper
Version: 1.1.1
Summary: A simple PayMongo API wrapper for Python.
Home-page: https://github.com/TopeMe/PaymongoWrapper
Author: Christopher I Ejada Jr
Author-email: topeejada1@gmail.com
Project-URL: Source, https://github.com/TopeMe/PaymongoWrapper
Keywords: paymongo payments api wrapper
Classifier: Development Status :: 3 - Alpha
Classifier: Intended Audience :: Developers
Classifier: Programming Language :: Python :: 3
Classifier: License :: OSI Approved :: MIT License
Classifier: Operating System :: OS Independent
Requires-Python: >=3.6
License-File: LICENSE
Requires-Dist: requests
Requires-Dist: python-dotenv
Dynamic: author
Dynamic: author-email
Dynamic: classifier
Dynamic: description
Dynamic: description-content-type
Dynamic: home-page
Dynamic: keywords
Dynamic: license-file
Dynamic: project-url
Dynamic: requires-dist
Dynamic: requires-python
Dynamic: summary
